odoo8_addon_product_media-8.0.1.0.0.99.dev13-py3.8-nspkg.pth
odoo_addons/product_media/README.rst
odoo_addons/product_media/__init__.py
odoo_addons/product_media/__openerp__.py
odoo_addons/product_media/data/ir_parameter.xml
odoo_addons/product_media/models/__init__.py
odoo_addons/product_media/models/product.py
odoo_addons/product_media/security/ir.model.access.csv
odoo_addons/product_media/views/product_menu.xml
odoo_addons/product_media/views/product_view.xml
odoo8_addon_product_media-8.0.1.0.0.99.dev13.dist-info/METADATA
odoo8_addon_product_media-8.0.1.0.0.99.dev13.dist-info/WHEEL
odoo8_addon_product_media-8.0.1.0.0.99.dev13.dist-info/namespace_packages.txt
odoo8_addon_product_media-8.0.1.0.0.99.dev13.dist-info/top_level.txt
odoo8_addon_product_media-8.0.1.0.0.99.dev13.dist-info/RECORD
